setup.py
SpoofMAC.egg-info/PKG-INFO
SpoofMAC.egg-info/SOURCES.txt
SpoofMAC.egg-info/dependency_links.txt
SpoofMAC.egg-info/requires.txt
SpoofMAC.egg-info/top_level.txt
scripts/spoof-mac.py
spoofmac/__init__.py
spoofmac/interface.py
spoofmac/util.py
spoofmac/version.py