Metadata-Version: 1.0
Name: SpoofMAC
Version: 2.0.0
Summary: 
